huey_mongodb-1.1.0.dist-info/METADATA
huey_mongodb-1.1.0.dist-info/WHEEL
huey_mongodb-1.1.0.dist-info/entry_points.txt
huey_mongodb/__init__.py
huey_mongodb-1.1.0.dist-info/RECORD
